MissButterfly/__init__.py
MissButterfly/butterfly_mask.py
MissButterfly/caesar_cipher.py
MissButterfly/string_shuffler.py
missbutterfly-0.1.1.dist-info/licenses/LICENSE
missbutterfly-0.1.1.dist-info/METADATA
missbutterfly-0.1.1.dist-info/WHEEL
missbutterfly-0.1.1.dist-info/top_level.txt
missbutterfly-0.1.1.dist-info/RECORD
