Metadata-Version: 2.4
Name: MissButterfly
Version: 0.1.1
Summary: A package for reversible string obfuscation using Caesar cipher and deterministic shuffling.
Home-page: https://github.com/FireIndex/MissButterfly
Author: Sundram
Author-email: sundramkumar8298@gmail.com
License: MIT
Classifier: Programming Language :: Python :: 3
Classifier: License :: OSI Approved :: MIT License
Classifier: Operating System :: OS Independent
Requires-Python: >=3.7
License-File: LICENSE
Dynamic: author
Dynamic: author-email
Dynamic: classifier
Dynamic: description
Dynamic: description-content-type
Dynamic: home-page
Dynamic: license
Dynamic: license-file
Dynamic: requires-python
Dynamic: summary
